rbms/__init__.py
rbms/classes.py
rbms/const.py
rbms/correlations.py
rbms/custom_fn.py
rbms/io.py
rbms/map_model.py
rbms/parser.py
rbms/plot.py
rbms/utils.py
rbms/bernoulli_bernoulli/__init__.py
rbms/bernoulli_bernoulli/classes.py
rbms/bernoulli_bernoulli/functional.py
rbms/bernoulli_bernoulli/implement.py
rbms/dataset/__init__.py
rbms/dataset/dataset_class.py
rbms/dataset/fasta_utils.py
rbms/dataset/load_fasta.py
rbms/dataset/load_h5.py
rbms/dataset/parser.py
rbms/dataset/utils.py
rbms/metrics/__init__.py
rbms/metrics/aats.py
rbms/partition_function/ais.py
rbms/partition_function/exact.py
rbms/potts_bernoulli/__init__.py
rbms/potts_bernoulli/classes.py
rbms/potts_bernoulli/functional.py
rbms/potts_bernoulli/implement.py
rbms/potts_bernoulli/tools.py
rbms/potts_bernoulli/utils.py
rbms/sampling/gibbs.py
rbms/sampling/pt.py
rbms/scripts/__init__.py
rbms/scripts/entrypoint.py
rbms/scripts/pt_sampling.py
rbms/scripts/split_data.py
rbms/scripts/train_rbm.py
rbms/training/pcd.py
rbms/training/utils.py
rbms-0.5.0.dist-info/METADATA
rbms-0.5.0.dist-info/WHEEL
rbms-0.5.0.dist-info/entry_points.txt
rbms-0.5.0.dist-info/licenses/LICENSE
rbms-0.5.0.dist-info/RECORD
