Metadata-Version: 2.4
Name: rbms
Version: 0.5.0
Summary: Training and analyzing Restricted Boltzmann Machines in PyTorch
Project-URL: Homepage, https://github.com/DsysDML/rbms
Project-URL: Issues, https://github.com/DsysDML/rbms/issues
Author: Aurélien Decelle, Cyril Furtlehner, Alfonso Navas, Lorenzo Rosset, Beatriz Seoane
Author-email: Nicolas Béreux <nicolas.bereux@gmail.com>
Maintainer-email: Nicolas Béreux <nicolas.bereux@gmail.com>
License-File: LICENSE
Keywords: Restricted Boltzmann Machine,rbm
Classifier: License :: OSI Approved :: MIT License
Classifier: Operating System :: OS Independent
Classifier: Programming Language :: Python :: 3
Requires-Python: >=3.11
Requires-Dist: h5py>=3.12.0
Requires-Dist: matplotlib>=3.8.0
Requires-Dist: numpy>=2.0.0
Requires-Dist: torch>=2.5.0
Requires-Dist: tqdm>=4.65.0
